cups/__init__.py
cups/db.py
cups/models.py
cups/tasks.py
cups/utils.py
cups_python-0.1.3.dist-info/LICENSE
cups_python-0.1.3.dist-info/METADATA
cups_python-0.1.3.dist-info/WHEEL
cups_python-0.1.3.dist-info/top_level.txt
cups_python-0.1.3.dist-info/RECORD
