Metadata-Version: 2.1
Name: cups-python
Version: 0.1.3
Summary: Python 3.8 Cifrazia Ultimate Permission System
Home-page: https://github.com/AdamBrianBright/cups-python
Author: Adam Bright
Author-email: adam.brian.bright@gmail.com
License: UNKNOWN
Platform: UNKNOWN
Classifier: Programming Language :: Python :: 3.8
Classifier: Programming Language :: Python :: 3.9
Requires-Dist: py2neo (>=2021.0.1)
Requires-Dist: pytz (>=2021.1)
Requires-Dist: ujson (>=4.0.2)
